<?xml version="1.0"?>
<configuracion>
    <perfiles>
        <perfil>
            <nombre>musico</nombre>
            <palabrasClave>
                <palabra>guitarra</palabra>
                <palabra>bateria</palabra>
                <palabra>teclado</palabra>
                <palabra>voz</palabra>
                <palabra>cancion</palabra>
                <palabra>nota</palabra>
                <palabra>partitura</palabra>
                <palabra>ritmo</palabra>
                <palabra>melodia</palabra>
                <palabra>armonia</palabra>
                <palabra>estudio</palabra>
                <palabra>ensayo</palabra>
                <palabra>grabacion</palabra>
                <palabra>mezcla</palabra>
                <palabra>produccion</palabra>
                <palabra>disco</palabra>
                <palabra>concierto</palabra>
                <palabra>escenario</palabra>
                <palabra>audiencia</palabra>
                <palabra>interpretacion</palabra>
            </palabrasClave>
        </perfil>
        <perfil>
            <nombre>cocinero</nombre>
            <palabrasClave>
                <palabra>cuchillo</palabra>
                <palabra>sarten</palabra>
                <palabra>especias</palabra>
                <palabra>hornear</palabra>
                <palabra>degustacion</palabra>
            </palabrasClave>
        </perfil>

    </perfiles>
    <descartadas>
        <palabra>bodas</palabra>
        <palabra>oro</palabra>
        <palabra>saturno</palabra>
        <palabra>centenario</palabra>
        <palabra>trompeta</palabra>
    </descartadas>
</configuracion>